fast_alphashape-0.2.0.dist-info/METADATA
fast_alphashape-0.2.0.dist-info/WHEEL
fast_alphashape-0.2.0.dist-info/license_files/LICENSE
fast_alphashape.libs/libgfortran-040039e1.so.5
fast_alphashape.libs/libquadmath-96973f99.so.0
fast_alphashape/alphashape.py
fast_alphashape/__init__.py
fast_alphashape/_fast_alphashape.abi3.so
fast_alphashape-0.2.0.dist-info/RECORD
