Metadata-Version: 2.1
Name: fast-alphashape
Version: 0.2.0
Classifier: Programming Language :: Python
Classifier: Programming Language :: Python :: 3
Classifier: Programming Language :: Python :: 3 :: Only
Classifier: Programming Language :: Python :: 3.7
Classifier: Programming Language :: Python :: 3.8
Classifier: Programming Language :: Python :: 3.9
Classifier: Programming Language :: Python :: 3.10
Classifier: License :: OSI Approved :: MIT License
Classifier: Operating System :: POSIX :: Linux
Classifier: Operating System :: Microsoft :: Windows
Classifier: Operating System :: MacOS
Classifier: Topic :: Software Development :: Libraries :: Python Modules
Classifier: Typing :: Typed
Requires-Dist: numpy~=1.0
Requires-Dist: shapely~=1.0
Requires-Dist: geopandas
License-File: LICENSE
Summary: A Rust backed implementation for generating 2D alpha shapes from points
Author-email: Martin Black <18327836+mblackgeo@users.noreply.github.com>
Requires-Python: >=3.7
Project-URL: Homepage, https://github.com/mblackgeo/fast-alphashape
Project-URL: Repository, https://github.com/mblackgeo/fast-alphashape
